dvault/__init__.py
dvault/__main__.py
dvault/constants.py
dvault/db_engine.py
dvault/file_interface.py
dvault/operations.py
dvault/utils.py
dvault/vault_core.py
dvault-1.1.dist-info/LICENSE
dvault-1.1.dist-info/METADATA
dvault-1.1.dist-info/WHEEL
dvault-1.1.dist-info/top_level.txt
dvault-1.1.dist-info/RECORD
