Metadata-Version: 2.1
Name: dvault
Version: 1.1
Summary: To keep your data safe from others' eyes
Author-email: Gokul Raj <gokulraj059@gmail.com>
License: MIT License
Project-URL: Homepage, https://github.com/GokulRajV8/dvault
Keywords: vault,filestore,encryption
Classifier: Development Status :: 5 - Production/Stable
Classifier: Programming Language :: Python :: 3
Classifier: License :: OSI Approved :: MIT License
Classifier: Natural Language :: English
Classifier: Operating System :: OS Independent
Classifier: Topic :: Utilities
Requires-Python: >=3.12
License-File: LICENSE
Requires-Dist: cryptography
